README.txt
setup.py
docs/HISTORY.txt
docs/INSTALL.txt
docs/LICENSE.GPL
docs/LICENSE.txt
experimental/__init__.py
experimental.ulocalized_time.egg-info/PKG-INFO
experimental.ulocalized_time.egg-info/SOURCES.txt
experimental.ulocalized_time.egg-info/dependency_links.txt
experimental.ulocalized_time.egg-info/entry_points.txt
experimental.ulocalized_time.egg-info/namespace_packages.txt
experimental.ulocalized_time.egg-info/not-zip-safe
experimental.ulocalized_time.egg-info/requires.txt
experimental.ulocalized_time.egg-info/top_level.txt
experimental/ulocalized_time/__init__.py
experimental/ulocalized_time/configure.zcml
experimental/ulocalized_time/patches.py
experimental/ulocalized_time/tests.py