Metadata-Version: 1.0
Name: experimental.ulocalized-time
Version: 0.1.0
Summary: Experimental version for ulocalized_time Plone function, that extends the date/time formats
Home-page: http://svn.plone.org/svn/collective/experimental.ulocalized_time
Author: RedTurtle Technology
Author-email: sviluppoplone@redturtle.net
License: GPL
Keywords: plone date localization i18n plonegov i10n
Platform: UNKNOWN
Classifier: Framework :: Plone
Classifier: Development Status :: 3 - Alpha
Classifier: Programming Language :: Python
Classifier: Intended Audience :: Developers
Classifier: License :: OSI Approved :: GNU General Public License (GPL)
